[
    {
        "name": "C. Redalen",
        "pdga_number": 79748
    },
    {
        "name": "E. Robinson",
        "pdga_number": 50671
    },
    {
        "name": "A. Barela",
        "pdga_number": 44382
    },
    {
        "name": "C. Ellis",
        "pdga_number": 44512
    },
    {
        "name": "J. Anderson",
        "pdga_number": 122356
    },
    {
        "name": "A. Marwede",
        "pdga_number": 75590
    },
    {
        "name": "S. Withers",
        "pdga_number": 38464
    },
    {
        "name": "K. Jones",
        "pdga_number": 41760
    },
    {
        "name": "A. Gossage",
        "pdga_number": 35449
    },
    {
        "name": "M. Ford",
        "pdga_number": 72844
    },
    {
        "name": "D. Gibson",
        "pdga_number": 48346
    },
    {
        "name": "E. Smith",
        "pdga_number": 101574
    },
    {
        "name": "C. Hanrahan",
        "pdga_number": 58857
    },
    {
        "name": "M. Kajiyama",
        "pdga_number": 8139
    },
    {
        "name": "E. Keith",
        "pdga_number": 47472
    },
    {
        "name": "C. Kramer",
        "pdga_number": 139228
    },
    {
        "name": "A. Tamm",
        "pdga_number": 76669
    },
    {
        "name": "R. Burridge",
        "pdga_number": 96512
    },
    {
        "name": "P. Welck",
        "pdga_number": 39491
    },
    {
        "name": "G. Rathbun",
        "pdga_number": 60436
    },
    {
        "name": "G. Shue",
        "pdga_number": 68285
    },
    {
        "name": "N. Queen",
        "pdga_number": 68286
    },
    {
        "name": "P. Ulibarri",
        "pdga_number": 27171
    },
    {
        "name": "B. Sides",
        "pdga_number": 129963
    },
    {
        "name": "Z. Arlinghaus",
        "pdga_number": 65266
    },
    {
        "name": "C. White",
        "pdga_number": 81739
    },
    {
        "name": "J. McCray",
        "pdga_number": 9852
    },
    {
        "name": "J. McCray",
        "pdga_number": 9852
    },
    {
        "name": "P. Oman",
        "pdga_number": 34344
    },
    {
        "name": "D. Schlitter",
        "pdga_number": 80219
    },
    {
        "name": "L. Humphries",
        "pdga_number": 69424
    },
    {
        "name": "K. Crabtree",
        "pdga_number": 25596
    },
    {
        "name": "A. Scott",
        "pdga_number": 99246
    },
    {
        "name": "A. Fish",
        "pdga_number": 58320
    },
    {
        "name": "C. Pinegar",
        "pdga_number": 74719
    },
    {
        "name": "S. Schultz",
        "pdga_number": 79047
    },
    {
        "name": "J. Hebenheimer",
        "pdga_number": 43762
    },
    {
        "name": "L. Samson",
        "pdga_number": 59419
    },
    {
        "name": "M. Marchbanks",
        "pdga_number": 79753
    },
    {
        "name": "C. Goodpasture",
        "pdga_number": 26455
    },
    {
        "name": "B. Stemen",
        "pdga_number": 100815
    },
    {
        "name": "S. Conway",
        "pdga_number": 38603
    },
    {
        "name": "S. Conway",
        "pdga_number": 38603
    },
    {
        "name": "T. Gilbert",
        "pdga_number": 85850
    },
    {
        "name": "J. Chen",
        "pdga_number": 128836
    },
    {
        "name": "L. Hancock",
        "pdga_number": 103050
    },
    {
        "name": "C. Rock",
        "pdga_number": 73695
    },
    {
        "name": "Z. Nash",
        "pdga_number": 101197
    },
    {
        "name": "J. Notch",
        "pdga_number": 106915
    },
    {
        "name": "A. Olson",
        "pdga_number": 120743
    },
    {
        "name": "B. Brown",
        "pdga_number": 87673
    },
    {
        "name": "S. McIsack",
        "pdga_number": 73512
    },
    {
        "name": "D. Pfaff",
        "pdga_number": 98558
    },
    {
        "name": "L. Oberholtzer Hess",
        "pdga_number": 90439
    },
    {
        "name": "B. Poland",
        "pdga_number": 100708
    },
    {
        "name": "M. Johansen",
        "pdga_number": 20300
    },
    {
        "name": "M. Johansen",
        "pdga_number": 20300
    },
    {
        "name": "B. Schweberger",
        "pdga_number": 12989
    },
    {
        "name": "G. Hancock",
        "pdga_number": 49885
    },
    {
        "name": "A. Miranda",
        "pdga_number": 118426
    },
    {
        "name": "J. Courtis",
        "pdga_number": 56511
    },
    {
        "name": "J. Patin",
        "pdga_number": 56037
    },
    {
        "name": "F. Meza",
        "pdga_number": 100497
    },
    {
        "name": "C. O'Reilly",
        "pdga_number": 99648
    },
    {
        "name": "T. Reiss",
        "pdga_number": 47136
    },
    {
        "name": "T. Tanner",
        "pdga_number": 99053
    },
    {
        "name": "C. Ahrens",
        "pdga_number": 88279
    },
    {
        "name": "A. Carey",
        "pdga_number": 61770
    },
    {
        "name": "A. Anselmo",
        "pdga_number": 56579
    },
    {
        "name": "T. Love",
        "pdga_number": 89959
    },
    {
        "name": "N. Newton",
        "pdga_number": 47689
    },
    {
        "name": "N. Culver",
        "pdga_number": 43902
    },
    {
        "name": "H. Thompson",
        "pdga_number": 60259
    },
    {
        "name": "M. McKay",
        "pdga_number": 60972
    },
    {
        "name": "M. Dollar",
        "pdga_number": 26045
    },
    {
        "name": "M. Dollar",
        "pdga_number": 26045
    },
    {
        "name": "D. Hastings",
        "pdga_number": 33504
    },
    {
        "name": "A. Bates",
        "pdga_number": 130724
    },
    {
        "name": "M. Blakely",
        "pdga_number": 15410
    },
    {
        "name": "J. Kiep",
        "pdga_number": 68815
    },
    {
        "name": "J. Brown",
        "pdga_number": 140954
    },
    {
        "name": "S. Brinster",
        "pdga_number": 10628
    },
    {
        "name": "S. Brinster",
        "pdga_number": 10628
    },
    {
        "name": "K. Skinner",
        "pdga_number": 126344
    },
    {
        "name": "I. Groh",
        "pdga_number": 145831
    },
    {
        "name": "N. Gill",
        "pdga_number": 33838
    },
    {
        "name": "D. Feldman",
        "pdga_number": 84447
    },
    {
        "name": "S. Talbott",
        "pdga_number": 114877
    },
    {
        "name": "L. Stout",
        "pdga_number": 118179
    },
    {
        "name": "K. Fukuta",
        "pdga_number": 102802
    },
    {
        "name": "C. Montgomery",
        "pdga_number": 35876
    },
    {
        "name": "R. Sheldon",
        "pdga_number": 87836
    },
    {
        "name": "C. Colglazier",
        "pdga_number": 47407
    },
    {
        "name": "D. York",
        "pdga_number": 90615
    },
    {
        "name": "N. Duran",
        "pdga_number": 28359
    },
    {
        "name": "C. Bryant",
        "pdga_number": 130709
    },
    {
        "name": "B. Schick",
        "pdga_number": 7992
    },
    {
        "name": "B. Schick",
        "pdga_number": 7992
    },
    {
        "name": "Z. Crist",
        "pdga_number": 132070
    },
    {
        "name": "M. Jordt",
        "pdga_number": 77562
    },
    {
        "name": "I. Burchett",
        "pdga_number": 60435
    },
    {
        "name": "J. Stoll",
        "pdga_number": 68103
    },
    {
        "name": "L. Bitney",
        "pdga_number": 51242
    },
    {
        "name": "S. DiCarlo",
        "pdga_number": 115742
    },
    {
        "name": "S. Futrell",
        "pdga_number": 127351
    },
    {
        "name": "J. Cutshall",
        "pdga_number": 58026
    },
    {
        "name": "P. Green",
        "pdga_number": 168496
    },
    {
        "name": "J. Coghill",
        "pdga_number": 63364
    },
    {
        "name": "M. Kneece",
        "pdga_number": 66907
    },
    {
        "name": "C. Fuhrman",
        "pdga_number": 30655
    },
    {
        "name": "E. Haushalter",
        "pdga_number": 198245
    },
    {
        "name": "B. McLaughlin",
        "pdga_number": 87143
    },
    {
        "name": "D. Garber",
        "pdga_number": 138089
    },
    {
        "name": "J. Blair",
        "pdga_number": 52785
    },
    {
        "name": "S. Rico",
        "pdga_number": 4666
    },
    {
        "name": "S. Rico",
        "pdga_number": 4666
    },
    {
        "name": "D. Snelling",
        "pdga_number": 45739
    },
    {
        "name": "J. Rye",
        "pdga_number": 153363
    },
    {
        "name": "B. Whitehead",
        "pdga_number": 145870
    },
    {
        "name": "C. Caldwell",
        "pdga_number": 50024
    },
    {
        "name": "J. Chesser",
        "pdga_number": 96063
    },
    {
        "name": "T. Snyder",
        "pdga_number": 102057
    },
    {
        "name": "T. Schultz",
        "pdga_number": 56016
    },
    {
        "name": "Z. Letts",
        "pdga_number": 57544
    },
    {
        "name": "C. Messerschmidt",
        "pdga_number": 58814
    },
    {
        "name": "C. Moore",
        "pdga_number": 78268
    },
    {
        "name": "C. Shotwell",
        "pdga_number": 41918
    },
    {
        "name": "D. Albright",
        "pdga_number": 31173
    },
    {
        "name": "T. Weber",
        "pdga_number": 93823
    },
    {
        "name": "C. Marrington",
        "pdga_number": 272703
    },
    {
        "name": "E. Reppun",
        "pdga_number": 8467
    },
    {
        "name": "E. Ward",
        "pdga_number": 62387
    },
    {
        "name": "C. Harris",
        "pdga_number": 37146
    },
    {
        "name": "M. Thompson",
        "pdga_number": 125969
    },
    {
        "name": "C. Bruce",
        "pdga_number": 101944
    },
    {
        "name": "M. Barajas",
        "pdga_number": 71050
    },
    {
        "name": "C. Pettigrew",
        "pdga_number": 31818
    },
    {
        "name": "E. Kison",
        "pdga_number": 121422
    },
    {
        "name": "C. Sherbert",
        "pdga_number": 61977
    },
    {
        "name": "L. Ritter",
        "pdga_number": 44974
    },
    {
        "name": "D. Polk",
        "pdga_number": 27276
    },
    {
        "name": "D. Polk",
        "pdga_number": 27276
    },
    {
        "name": "R. Latta",
        "pdga_number": 51685
    },
    {
        "name": "C. Villa",
        "pdga_number": 58197
    },
    {
        "name": "C. Villa",
        "pdga_number": 58197
    },
    {
        "name": "C. Harvey",
        "pdga_number": 151744
    },
    {
        "name": "D. Beauchamp",
        "pdga_number": 76153
    },
    {
        "name": "D. Trunkey",
        "pdga_number": 28623
    },
    {
        "name": "J. O'Polka",
        "pdga_number": 88979
    },
    {
        "name": "C. Wehrheim",
        "pdga_number": 60399
    },
    {
        "name": "N. Johnson",
        "pdga_number": 138355
    },
    {
        "name": "Z. Johnson",
        "pdga_number": 50312
    },
    {
        "name": "D. Napier",
        "pdga_number": 31473
    },
    {
        "name": "D. Napier",
        "pdga_number": 31473
    },
    {
        "name": "E. Pierce",
        "pdga_number": 123319
    },
    {
        "name": "J. DiBattista",
        "pdga_number": 86089
    },
    {
        "name": "C. Robbins",
        "pdga_number": 109674
    },
    {
        "name": "G. Phillips",
        "pdga_number": 119504
    }
]